envoy/distribution/repo/__init__.py
envoy/distribution/repo/abstract.py
envoy/distribution/repo/cmd.py
envoy/distribution/repo/deb.py
envoy/distribution/repo/exceptions.py
envoy/distribution/repo/py.typed
envoy/distribution/repo/runner.py
envoy.distribution.repo-0.0.8.dist-info/METADATA
envoy.distribution.repo-0.0.8.dist-info/WHEEL
envoy.distribution.repo-0.0.8.dist-info/entry_points.txt
envoy.distribution.repo-0.0.8.dist-info/namespace_packages.txt
envoy.distribution.repo-0.0.8.dist-info/top_level.txt
envoy.distribution.repo-0.0.8.dist-info/RECORD
