Metadata-Version: 2.1
Name: envoy.distribution.repo
Version: 0.0.8
Summary: "Release publishing tool used in Envoy proxy's CI"
Home-page: https://github.com/envoyproxy/pytooling/tree/main/envoy.distribution.repo
Author: Ryan Northey
Author-email: ryan@synca.io
Maintainer: Ryan Northey
Maintainer-email: ryan@synca.io
License: Apache Software License 2.0
Platform: UNKNOWN
Requires-Dist: abstracts (>=0.0.12)
Requires-Dist: aio.core (>=0.9.1)
Requires-Dist: aio.run.runner (>=0.3.3)
Requires-Dist: envoy.base.utils (>=0.3.9)
Requires-Dist: verboselogs
